{
	"info": {
		"_postman_id": "2250d8fa-6c50-4f00-b0f5-32f01513aec9",
		"name": "API 1-V2-V3",
		"schema": "https://schema.getpostman.com/json/collection/v2.1.0/collection.json"
	},
	"item": [
		{
			"name": "Sample endpoint: Returns details about a particular user",
			"id": "d2841073-a25f-490d-b84d-535f56d5bc35",
			"protocolProfileBehavior": {
				"disableBodyPruning": true
			},
			"request": {
				"method": "GET",
				"header": [
					{
						"key": "Accept",
						"value": "application/json"
					}
				],
				"url": {
					"raw": "{{baseUrl}}/user?id=-70421140",
					"host": [
						"{{baseUrl}}"
					],
					"path": [
						"user"
					],
					"query": [
						{
							"key": "id",
							"value": "-70421140",
							"description": "(Required) ID of the user"
						}
					]
				}
			},
			"response": [
				{
					"id": "4bc6aa5f-e5ba-494c-8276-4a983ce00818",
					"name": "Sample response: Details about a user by ID",
					"originalRequest": {
						"method": "GET",
						"header": [
							{
								"description": "Added as a part of security scheme: basic",
								"key": "Authorization",
								"value": "Basic <credentials>"
							}
						],
						"url": {
							"raw": "{{baseUrl}}/user?id=-70421140",
							"host": [
								"{{baseUrl}}"
							],
							"path": [
								"user"
							],
							"query": [
								{
									"key": "id",
									"value": "-70421140"
								}
							]
						}
					},
					"status": "OK",
					"code": 200,
					"_postman_previewlanguage": "json",
					"header": [
						{
							"disabled": false,
							"description": "A link to the next page of responses",
							"key": "x-next",
							"value": "esse officia"
						},
						{
							"key": "Content-Type",
							"value": "application/json"
						}
					],
					"cookie": [],
					"responseTime": null,
					"body": "{\n  \"id\": 66252542,\n  \"name\": \"nulla do irure\",\n  \"tag\": \"sit tempor ut\"\n}"
				},
				{
					"id": "e94bb060-2d9b-4695-afad-ff7d6964fd0f",
					"name": "Unexpected error",
					"originalRequest": {
						"method": "GET",
						"header": [
							{
								"description": "Added as a part of security scheme: basic",
								"key": "Authorization",
								"value": "Basic <credentials>"
							}
						],
						"url": {
							"raw": "{{baseUrl}}/user?id=-70421140",
							"host": [
								"{{baseUrl}}"
							],
							"path": [
								"user"
							],
							"query": [
								{
									"key": "id",
									"value": "-70421140"
								}
							]
						}
					},
					"status": "Internal Server Error",
					"code": 500,
					"_postman_previewlanguage": "json",
					"header": [
						{
							"key": "Content-Type",
							"value": "application/json"
						}
					],
					"cookie": [],
					"responseTime": null,
					"body": "{\n  \"code\": -45662904,\n  \"message\": \"dolore incididunt ad\"\n}"
				}
			]
		}
	],
	"auth": {
		"type": "basic",
		"basic": [
			{
				"key": "username",
				"value": "<Basic Auth Username>",
				"type": "string"
			},
			{
				"key": "password",
				"value": "<Basic Auth Password>",
				"type": "string"
			}
		]
	},
	"variable": [
		{
			"id": "38f75d16-f967-4467-91c2-7012afb1e1b7",
			"key": "baseUrl",
			"value": "localhost:3000",
			"type": "string"
		}
	]
}